redis_cache_py/__init__.py
redis_cache_py/functional.py
redis_cache_py/utils.py
redis_cache_py/asyncio/__init__.py
tests/__init__.py
tests/test_cache.py
tests/test_connection.py
tests/test_singleton.py
redis_cache_py-0.0.2.dist-info/LICENSE
redis_cache_py-0.0.2.dist-info/METADATA
redis_cache_py-0.0.2.dist-info/WHEEL
redis_cache_py-0.0.2.dist-info/top_level.txt
redis_cache_py-0.0.2.dist-info/RECORD
