Metadata-Version: 2.1
Name: redis-cache-py
Version: 0.0.2
Summary: Redis Cache For Python
Home-page: https://github.com/ptran1203/py-redis-cache
Author: Phat Tran
Author-email: phatth1203@gmail.com
Project-URL: Bug Tracker, https://github.com/ptran1203/py-redis-cache/issues
Classifier: Programming Language :: Python :: 3
Classifier: License :: OSI Approved :: MIT License
Classifier: Operating System :: OS Independent
Requires-Python: >=3.6
License-File: LICENSE
Requires-Dist: redis >=5.0.0
